setup.py
import_descendants/__init__.py
import_descendants/models.py
import_descendants/tests.py
import_descendants/views.py
import_descendants.egg-info/PKG-INFO
import_descendants.egg-info/SOURCES.txt
import_descendants.egg-info/dependency_links.txt
import_descendants.egg-info/top_level.txt
import_descendants/test_example/__init__.py
import_descendants/test_example/child_file.py
import_descendants/test_example/child_dir/__init__.py
import_descendants/test_example/child_dir/grandchild_file.py
import_descendants/test_example/child_dir/grandchild_dir/__init__.py