Metadata-Version: 1.0
Name: import-descendants
Version: 1.0.0
Summary: Automatically import all of a module's descendants
Home-page: http://github.com/brightinteractive/import-descendants/
Author: Bright Interactive
Author-email: francis@bright-interactive.co.uk
License: BSD
Platform: UNKNOWN
